quave_sdk/__init__.py
quave_sdk/job.c
quave_sdk/job.cpython-313-darwin.so
quave_sdk/job.py
quave_sdk/job_execution.c
quave_sdk/job_execution.cpython-313-darwin.so
quave_sdk/job_execution.py
quave_sdk/quave.c
quave_sdk/quave.cpython-313-darwin.so
quave_sdk/quave.py
quave_sdk-0.1.2.dist-info/licenses/LICENSE
quave_sdk-0.1.2.dist-info/METADATA
quave_sdk-0.1.2.dist-info/WHEEL
quave_sdk-0.1.2.dist-info/top_level.txt
quave_sdk-0.1.2.dist-info/RECORD
