Metadata-Version: 2.4
Name: quave-sdk
Version: 0.1.2
Summary: Python SDK for the Quave quantum computing platform
Author: Quave
License-Expression: GPL-3.0-or-later
Project-URL: Homepage, https://quave.qaion.com
Project-URL: Documentation, https://quave.qaion.com/documentation
Requires-Python: >=3.8
License-File: LICENSE
Requires-Dist: requests
Requires-Dist: qiskit
Requires-Dist: supabase
Dynamic: license-file
